dep_logic-0.4.8.dist-info/METADATA
dep_logic-0.4.8.dist-info/WHEEL
dep_logic-0.4.8.dist-info/entry_points.txt
dep_logic-0.4.8.dist-info/licenses/LICENSE
dep_logic/__init__.py
dep_logic/markers/__init__.py
dep_logic/markers/any.py
dep_logic/markers/base.py
dep_logic/markers/empty.py
dep_logic/markers/multi.py
dep_logic/markers/single.py
dep_logic/markers/union.py
dep_logic/markers/utils.py
dep_logic/py.typed
dep_logic/specifiers/__init__.py
dep_logic/specifiers/arbitrary.py
dep_logic/specifiers/base.py
dep_logic/specifiers/generic.py
dep_logic/specifiers/range.py
dep_logic/specifiers/special.py
dep_logic/specifiers/union.py
dep_logic/tags/__init__.py
dep_logic/tags/os.py
dep_logic/tags/platform.py
dep_logic/tags/tags.py
dep_logic/utils.py
dep_logic-0.4.8.dist-info/RECORD
